scc_access/__init__.py
scc_access/scc_access.py
scc_access-0.11.0.dist-info/LICENCE.txt
scc_access-0.11.0.dist-info/METADATA
scc_access-0.11.0.dist-info/WHEEL
scc_access-0.11.0.dist-info/entry_points.txt
scc_access-0.11.0.dist-info/top_level.txt
scc_access-0.11.0.dist-info/RECORD
