Metadata-Version: 2.1
Name: scc-access
Version: 0.11.0
Summary: Package for interacting with EARLINET's Single Calculus Chain through the command line.
Home-page: https://repositories.imaa.cnr.it/public/scc_access/
Author: Ioannis Binietoglou
Author-email: ioannis@inoe.ro
License: MIT
Keywords: lidar aerosol SCC
Platform: UNKNOWN
Classifier: Development Status :: 4 - Beta
Classifier: License :: OSI Approved :: MIT License
Classifier: Programming Language :: Python :: 3
Classifier: Intended Audience :: Science/Research
Classifier: Topic :: Scientific/Engineering :: Atmospheric Science
Requires-Dist: requests
Requires-Dist: pyyaml
Requires-Dist: netCDF4
